LICENSE
README.md
pyproject.toml
setup.cfg
setup.py
src/phat/__init__.py
src/phat/dists.py
src/phat/thold.py
src/phat/tseries.py
src/phat/utils.py
src/phat/bootstrap/__init__.py
src/phat/bootstrap/numpy.py
src/phat/bootstrap/tf.py
src/phat/learn/__init__.py
src/phat/learn/dists.py
src/phat/learn/normnet.py
src/phat/learn/phatnet.py
src/phat/learn/utils.py
src/phat_tails.egg-info/PKG-INFO
src/phat_tails.egg-info/SOURCES.txt
src/phat_tails.egg-info/dependency_links.txt
src/phat_tails.egg-info/requires.txt
src/phat_tails.egg-info/top_level.txt