Metadata-Version: 2.1
Name: phat-tails
Version: 0.0.9
Summary: Pareto Hybrids with Asymmetric Tails
Home-page: https://github.com/rskene/phat
License: MIT License
Platform: UNKNOWN
Classifier: License :: OSI Approved :: BSD License
Classifier: Programming Language :: Python :: 3
Classifier: Programming Language :: Python :: 3.9
Requires-Python: >=3.9
License-File: LICENSE
